smoothed_sphere/__init__.py
smoothed_sphere/smoothed_sphere.py
smoothed_sphere-0.4.dist-info/METADATA
smoothed_sphere-0.4.dist-info/WHEEL
smoothed_sphere-0.4.dist-info/top_level.txt
smoothed_sphere-0.4.dist-info/RECORD
